lnrun/__init__.py
lnrun/__main__.py
lnrun/__version__.py
lnrun/cli.py
lnrun/config.py
lnrun/get_configs.py
lnrun/run.py
lnrun/send_image.py
lnrun/send_message.py
lnrun/set_config.py
lnrun-0.1.6.dist-info/LICENSE
lnrun-0.1.6.dist-info/METADATA
lnrun-0.1.6.dist-info/WHEEL
lnrun-0.1.6.dist-info/entry_points.txt
lnrun-0.1.6.dist-info/top_level.txt
lnrun-0.1.6.dist-info/RECORD
