Metadata-Version: 2.1
Name: lnrun
Version: 0.1.6
Summary: Notify via LineNotify after running system commands.
Home-page: https://github.com/jayshihchou/lnrun
Author: Chou, Shih-Chieh
Author-email: jayshihchou@gmail.com
License: MIT
Keywords: line,notify,linenotify,lnrun
Classifier: License :: OSI Approved :: MIT License
Classifier: Programming Language :: Python
Classifier: Programming Language :: Python :: 3
Classifier: Programming Language :: Python :: 3.7
Classifier: Programming Language :: Python :: 3.8
Classifier: Programming Language :: Python :: 3.9
Classifier: Operating System :: Microsoft :: Windows
Classifier: Operating System :: POSIX :: Linux
Classifier: Operating System :: MacOS
Requires-Python: >=3.6
License-File: LICENSE
